dvc_render/__init__.py
dvc_render/base.py
dvc_render/exceptions.py
dvc_render/html.py
dvc_render/image.py
dvc_render/markdown.py
dvc_render/plotly.py
dvc_render/table.py
dvc_render/utils.py
dvc_render/vega.py
dvc_render/vega_templates.py
dvc_render-1.0.2.dist-info/LICENSE
dvc_render-1.0.2.dist-info/METADATA
dvc_render-1.0.2.dist-info/WHEEL
dvc_render-1.0.2.dist-info/top_level.txt
dvc_render-1.0.2.dist-info/RECORD
