Metadata-Version: 2.1
Name: dvc-render
Version: 1.0.2
Summary: Dvc Render
Author-email: Iterative <support@dvc.org>
License: Apache-2.0
Project-URL: Issues, https://github.com/iterative/dvc-render/issues
Project-URL: Source, https://github.com/iterative/dvc-render
Classifier: Programming Language :: Python :: 3
Classifier: Programming Language :: Python :: 3.9
Classifier: Programming Language :: Python :: 3.10
Classifier: Programming Language :: Python :: 3.11
Classifier: Programming Language :: Python :: 3.12
Classifier: Development Status :: 4 - Beta
Requires-Python: >=3.9
License-File: LICENSE
Provides-Extra: table
Requires-Dist: tabulate>=0.8.7; extra == "table"
Requires-Dist: flatten_dict<1,>=0.4.1; extra == "table"
Provides-Extra: markdown
Requires-Dist: dvc-render[table]; extra == "markdown"
Requires-Dist: matplotlib; extra == "markdown"
Provides-Extra: docs
Requires-Dist: mkdocs<2,>=1.5.2; extra == "docs"
Requires-Dist: mkdocs-gen-files<1,>=0.5.0; extra == "docs"
Requires-Dist: mkdocs-material<10,>=9.3.1; extra == "docs"
Requires-Dist: mkdocs-section-index<1,>=0.3.6; extra == "docs"
Requires-Dist: mkdocstrings-python<2,>=1.6.3; extra == "docs"
Provides-Extra: tests
Requires-Dist: dvc-render[markdown,table]; extra == "tests"
Requires-Dist: pytest<9,>=7; extra == "tests"
Requires-Dist: pytest-cov>=4.1.0; extra == "tests"
Requires-Dist: pytest-sugar; extra == "tests"
Requires-Dist: pytest-mock; extra == "tests"
Provides-Extra: dev
Requires-Dist: dvc-render[docs,tests]; extra == "dev"
Requires-Dist: mypy==1.9.0; extra == "dev"
